prk_scraping_bib/__init__.py
prk_scraping_bib/logging_config.py
prk_scraping_bib/scraper.py
prk_scraping_bib/selenium_helpers.py
prk_scraping_bib/utils.py
prk_scraping_bib-0.2.9.dist-info/METADATA
prk_scraping_bib-0.2.9.dist-info/WHEEL
prk_scraping_bib-0.2.9.dist-info/entry_points.txt
prk_scraping_bib-0.2.9.dist-info/top_level.txt
prk_scraping_bib-0.2.9.dist-info/RECORD
