Metadata-Version: 2.1
Name: prk_scraping_bib
Version: 0.2.9
Summary: Primark scraping
Home-page: https://github.com/tbeninnovation/webScrapping
Author: latris
Author-email: abde4872@gmail.com
Classifier: Programming Language :: Python :: 3
Classifier: License :: OSI Approved :: MIT License
Classifier: Operating System :: OS Independent
Requires-Dist: curl-cffi
Requires-Dist: beautifulsoup4
Requires-Dist: pandas
Requires-Dist: selenium
Requires-Dist: requests
